cubicweb_calendar/__init__.py
cubicweb_calendar/__pkginfo__.py
cubicweb_calendar/entities.py
cubicweb_calendar/schema.py
cubicweb_calendar/data/cubes.calendar.css
cubicweb_calendar/data/office-calendar.png
cubicweb_calendar/i18n/en.po
cubicweb_calendar/i18n/es.po
cubicweb_calendar/i18n/fr.po
cubicweb_calendar/migration/0.11.0_Any.py
cubicweb_calendar/migration/0.4.0_Any.py
cubicweb_calendar/migration/postcreate.py
cubicweb_calendar/views/__init__.py
cubicweb_calendar/views/facets.py
cubicweb_calendar/views/main.py
cubicweb_calendar/views/primaries.py
cubicweb_calendar/views/secondaries.py
cubicweb_calendar-1.1.0.dist-info/METADATA
cubicweb_calendar-1.1.0.dist-info/WHEEL
cubicweb_calendar-1.1.0.dist-info/entry_points.txt
cubicweb_calendar-1.1.0.dist-info/top_level.txt
cubicweb_calendar-1.1.0.dist-info/RECORD
